ShellBianchengFanli/README.md
ShellBianchengFanli/__init__.py
ShellBianchengFanli/__main__.py
ShellBianchengFanli/file.epub
ShellBianchengFanli/index.html
ShellBianchengFanli/css/__init__.py
ShellBianchengFanli/css/annotations.css
ShellBianchengFanli/css/main.css
ShellBianchengFanli/css/normalize.css
ShellBianchengFanli/css/popup.css
ShellBianchengFanli/font/__init__.py
ShellBianchengFanli/font/fontello.eot
ShellBianchengFanli/font/fontello.svg
ShellBianchengFanli/font/fontello.ttf
ShellBianchengFanli/font/fontello.woff
ShellBianchengFanli/img/__init__.py
ShellBianchengFanli/img/annotator-glyph-sprite.png
ShellBianchengFanli/img/annotator-icon-sprite.png
ShellBianchengFanli/img/apple-touch-icon.png
ShellBianchengFanli/img/cancelfullscreen.png
ShellBianchengFanli/img/close.png
ShellBianchengFanli/img/fullscreen.png
ShellBianchengFanli/img/loader.gif
ShellBianchengFanli/img/menu-icon.png
ShellBianchengFanli/img/save.png
ShellBianchengFanli/img/saved.png
ShellBianchengFanli/img/settings-s.png
ShellBianchengFanli/img/settings.png
ShellBianchengFanli/img/star.png
ShellBianchengFanli/js/__init__.py
ShellBianchengFanli/js/epub.js
ShellBianchengFanli/js/epub.min.js
ShellBianchengFanli/js/epub.min.map
ShellBianchengFanli/js/hooks.min.js
ShellBianchengFanli/js/hooks.min.map
ShellBianchengFanli/js/reader.js
ShellBianchengFanli/js/reader.js.map
ShellBianchengFanli/js/reader.min.js
ShellBianchengFanli/js/reader.min.map
ShellBianchengFanli/js/hooks/__init__.py
ShellBianchengFanli/js/hooks/extensions/__init__.py
ShellBianchengFanli/js/hooks/extensions/highlight.js
ShellBianchengFanli/js/libs/__init__.py
ShellBianchengFanli/js/libs/jquery.min.js
ShellBianchengFanli/js/libs/localforage.min.js
ShellBianchengFanli/js/libs/screenfull.js
ShellBianchengFanli/js/libs/screenfull.min.js
ShellBianchengFanli/js/libs/zip.min.js
ShellBianchengFanli/js/plugins/__init__.py
ShellBianchengFanli/js/plugins/hypothesis.js
ShellBianchengFanli/js/plugins/search.js
shell_biancheng_fanli-2024.3.2.0.dist-info/METADATA
shell_biancheng_fanli-2024.3.2.0.dist-info/WHEEL
shell_biancheng_fanli-2024.3.2.0.dist-info/entry_points.txt
shell_biancheng_fanli-2024.3.2.0.dist-info/top_level.txt
shell_biancheng_fanli-2024.3.2.0.dist-info/RECORD
